pyloch/__init__.py
pyloch/core.py
pyloch-0.1.2.dist-info/licenses/LICENSE
pyloch-0.1.2.dist-info/METADATA
pyloch-0.1.2.dist-info/WHEEL
pyloch-0.1.2.dist-info/top_level.txt
pyloch-0.1.2.dist-info/RECORD
