Metadata-Version: 2.4
Name: pyloch
Version: 0.1.2
Summary: هذا المكتبه تحت اشراف حسو ال علي وتحت التطوير حاليا سيتم اضافه تحديثات جديده كل يوم
Author: Hasneen Qusay
Author-email: lyhasneen70@gmail.com
License: MIT
Requires-Python: >=3.7
License-File: LICENSE
Dynamic: author
Dynamic: author-email
Dynamic: license
Dynamic: license-file
Dynamic: requires-python
Dynamic: summary
